{
    "telemetry.sqmId": "",
    "telemetry.machineId": "e78f9232bd0e5ecbf8351372cccd10b2e0257ae66c380c831fc83fd620fbcf95",
    "telemetry.devDeviceId": "5bb9edee-288d-419a-acf5-c7c56ec526ef",
    "backupWorkspaces": {
        "workspaces": [],
        "folders": [
            {
                "folderUri": "file:///home/mution/School/Summer%20Semester%202025/ECON%20201M%20%5BPrinciples%20of%20Macroeconomics%5D"
            }
        ],
        "emptyWindows": [
            {
                "backupFolder": "1751576984889"
            }
        ]
    },
    "windowControlHeight": 35,
    "profileAssociations": {
        "workspaces": {
            "file:///home/mution/School/Summer%20Semester%202025/ECON%20201M%20%5BPrinciples%20of%20Macroeconomics%5D": "__default__profile__"
        },
        "emptyWindows": {
            "1751576984889": "__default__profile__"
        }
    },
    "windowsState": {
        "lastActiveWindow": {
            "folder": "file:///home/mution/School/Summer%20Semester%202025/ECON%20201M%20%5BPrinciples%20of%20Macroeconomics%5D",
            "backupPath": "/home/mution/.config/Code - OSS/Backups/cc03ed2b27754857917d12df3a27ea5e",
            "uiState": {
                "mode": 1,
                "x": 12,
                "y": 12,
                "width": 1256,
                "height": 696
            }
        },
        "openedWindows": []
    },
    "theme": "vs-dark",
    "themeBackground": "#1f1f1f",
    "windowSplash": {
        "zoomLevel": 0,
        "baseTheme": "vs-dark",
        "colorInfo": {
            "foreground": "#cccccc",
            "background": "#1f1f1f",
            "editorBackground": "#1f1f1f",
            "titleBarBackground": "#181818",
            "titleBarBorder": "#2b2b2b",
            "activityBarBackground": "#181818",
            "activityBarBorder": "#2b2b2b",
            "sideBarBackground": "#181818",
            "sideBarBorder": "#2b2b2b",
            "statusBarBackground": "#181818",
            "statusBarBorder": "#2b2b2b",
            "statusBarNoFolderBackground": "#1f1f1f"
        },
        "layoutInfo": {
            "sideBarSide": "left",
            "editorPartMinWidth": 220,
            "titleBarHeight": 35,
            "activityBarWidth": 48,
            "sideBarWidth": 170,
            "auxiliarySideBarWidth": 0,
            "statusBarHeight": 22,
            "windowBorder": false
        }
    },
    "windowSplashWorkspaceOverride": {
        "layoutInfo": {
            "sideBarWidth": 170,
            "auxiliaryBarWidth": 300,
            "workspaces": {
                "e48f2e82c265ee9636f5d77ca4ad073a": {
                    "sideBarVisible": true,
                    "auxiliaryBarVisible": false
                }
            }
        }
    }
}